{
    "links": [
        {
            "source": "핵소 고지",
            "target": "랜드 오브 마인",
            "value": 1.7724413950829045,
            "total": 3498,
            "same": 62
        },
        {
            "source": "온리 더 브레이브",
            "target": "랜드 오브 마인",
            "value": 1.4157973174366618,
            "total": 1342,
            "same": 19
        },
        {
            "source": "뚜르: 내 생애 최고의 49일",
            "target": "랜드 오브 마인",
            "value": 1.4157014157014158,
            "total": 777,
            "same": 11
        },
        {
            "source": "미스 슬로운",
            "target": "랜드 오브 마인",
            "value": 1.406799531066823,
            "total": 1706,
            "same": 24
        },
        {
            "source": "랜드 오브 마인",
            "target": "특전 유보트",
            "value": 1.392757660167131,
            "total": 718,
            "same": 10
        },
        {
            "source": "랜드 오브 마인",
            "target": "나, 다니엘 블레이크",
            "value": 1.3193812556869882,
            "total": 2198,
            "same": 29
        },
        {
            "source": "랜드 오브 마인",
            "target": "히든 피겨스",
            "value": 1.3189132155104195,
            "total": 3791,
            "same": 50
        },
        {
            "source": "랜드 오브 마인",
            "target": "프리 윌리",
            "value": 1.293103448275862,
            "total": 696,
            "same": 9
        },
        {
            "source": "랜드 오브 마인",
            "target": "어메이징 메리",
            "value": 1.2919896640826873,
            "total": 1161,
            "same": 15
        },
        {
            "source": "랜드 오브 마인",
            "target": "사랑과 영혼",
            "value": 1.232394366197183,
            "total": 1136,
            "same": 14
        },
        {
            "source": "랜드 오브 마인",
            "target": "로미오와 줄리엣",
            "value": 1.1961722488038278,
            "total": 836,
            "same": 10
        },
        {
            "source": "로보캅",
            "target": "랜드 오브 마인",
            "value": 1.1782032400589102,
            "total": 679,
            "same": 8
        },
        {
            "source": "내 어깨 위 고양이, 밥",
            "target": "랜드 오브 마인",
            "value": 1.164021164021164,
            "total": 945,
            "same": 11
        },
        {
            "source": "랜드 오브 마인",
            "target": "땐뽀걸즈",
            "value": 1.1614401858304297,
            "total": 861,
            "same": 10
        },
        {
            "source": "랜드 오브 마인",
            "target": "로마의 휴일",
            "value": 1.1587485515643106,
            "total": 863,
            "same": 10
        },
        {
            "source": "벤허",
            "target": "랜드 오브 마인",
            "value": 1.1251758087201125,
            "total": 1422,
            "same": 16
        }
    ],
    "nodes": [
        {
            "id": "히든 피겨스",
            "group": 1,
            "href": "/movie/bi/mi/basic.nhn?code=147092",
            "genre": [
                "드라마"
            ],
            "director": [
                "데오도르 멜피"
            ],
            "actor": [
                "타라지 P. 헨슨",
                "옥타비아 스펜서",
                "자넬 모네"
            ]
        },
        {
            "id": "미스 슬로운",
            "group": 1,
            "href": "/movie/bi/mi/basic.nhn?code=142632",
            "genre": [
                "드라마",
                "스릴러"
            ],
            "director": [
                "존 매든"
            ],
            "actor": [
                "제시카 차스테인"
            ]
        },
        {
            "id": "프리 윌리",
            "group": 2,
            "href": "/movie/bi/mi/basic.nhn?code=16466",
            "genre": [
                "가족",
                "모험",
                "드라마"
            ],
            "director": [
                "사이먼 윈서"
            ],
            "actor": [
                "케이코",
                "제이슨 제임스 리처",
                "로리 페티"
            ]
        },
        {
            "id": "온리 더 브레이브",
            "group": 1,
            "href": "/movie/bi/mi/basic.nhn?code=151752",
            "genre": [
                "드라마"
            ],
            "director": [
                "조셉 코신스키"
            ],
            "actor": [
                "조슈 브롤린",
                "마일즈 텔러",
                "제프 브리지스"
            ]
        },
        {
            "id": "로미오와 줄리엣",
            "group": 1,
            "href": "/movie/bi/mi/basic.nhn?code=10185",
            "genre": [
                "드라마",
                "멜로/로맨스"
            ],
            "director": [
                "프랑코 제페렐리"
            ],
            "actor": [
                "레너드 위팅",
                "올리비아 핫세",
                "존 맥에너리"
            ]
        },
        {
            "id": "나, 다니엘 블레이크",
            "group": 1,
            "href": "/movie/bi/mi/basic.nhn?code=150376",
            "genre": [
                "드라마"
            ],
            "director": [
                "켄 로치"
            ],
            "actor": [
                "데이브 존스",
                "헤일리 스콰이어"
            ]
        },
        {
            "id": "로보캅",
            "group": 3,
            "href": "/movie/bi/mi/basic.nhn?code=10217",
            "genre": [
                "SF",
                "액션",
                "범죄"
            ],
            "director": [
                "폴 버호벤"
            ],
            "actor": [
                "피터 웰러",
                "낸시 알렌",
                "댄 오헐리히"
            ]
        },
        {
            "id": "땐뽀걸즈",
            "group": 4,
            "href": "/movie/bi/mi/basic.nhn?code=167107",
            "genre": [
                "다큐멘터리"
            ],
            "director": [
                "이승문"
            ],
            "actor": [
                "이규호",
                "김현빈",
                "박혜영"
            ]
        },
        {
            "id": "로마의 휴일",
            "group": 5,
            "href": "/movie/bi/mi/basic.nhn?code=10101",
            "genre": [
                "코미디",
                "드라마",
                "멜로/로맨스"
            ],
            "director": [
                "윌리엄 와일러"
            ],
            "actor": [
                "그레고리 펙",
                "오드리 헵번"
            ]
        },
        {
            "id": "어메이징 메리",
            "group": 1,
            "href": "/movie/bi/mi/basic.nhn?code=143469",
            "genre": [
                "드라마"
            ],
            "director": [
                "마크 웹"
            ],
            "actor": [
                "크리스 에반스",
                "맥케나 그레이스",
                "린제이 던칸"
            ]
        },
        {
            "id": "핵소 고지",
            "group": 1,
            "href": "/movie/bi/mi/basic.nhn?code=142305",
            "genre": [
                "드라마",
                "전쟁",
                "멜로/로맨스"
            ],
            "director": [
                "멜 깁슨"
            ],
            "actor": [
                "앤드류 가필드",
                "샘 워싱턴",
                "휴고 위빙"
            ]
        },
        {
            "id": "랜드 오브 마인",
            "group": 1,
            "href": "/movie/bi/mi/basic.nhn?code=144100",
            "genre": [
                "드라마",
                "전쟁"
            ],
            "director": [
                "마틴 잔드블리엣"
            ],
            "actor": [
                "로랜드 몰러",
                "미켈 폴스라르",
                "루이스 호프만"
            ]
        },
        {
            "id": "특전 유보트",
            "group": 1,
            "href": "/movie/bi/mi/basic.nhn?code=10647",
            "genre": [
                "드라마",
                "전쟁"
            ],
            "director": [
                "볼프강 페터젠"
            ],
            "actor": [
                "주겐 프로크노",
                "클라우스 웨네먼",
                "허버트 그로네메이어"
            ]
        },
        {
            "id": "사랑과 영혼",
            "group": 6,
            "href": "/movie/bi/mi/basic.nhn?code=10173",
            "genre": [
                "멜로/로맨스",
                "드라마"
            ],
            "director": [
                "제리 주커"
            ],
            "actor": [
                "패트릭 스웨이지",
                "데미 무어"
            ]
        },
        {
            "id": "내 어깨 위 고양이, 밥",
            "group": 1,
            "href": "/movie/bi/mi/basic.nhn?code=154379",
            "genre": [
                "드라마"
            ],
            "director": [
                "로저 스포티스우드"
            ],
            "actor": [
                "루크 트레더웨이"
            ]
        },
        {
            "id": "뚜르: 내 생애 최고의 49일",
            "group": 4,
            "href": "/movie/bi/mi/basic.nhn?code=142304",
            "genre": [
                "다큐멘터리"
            ],
            "director": [
                "임정하",
                "전일우",
                "박형준"
            ],
            "actor": [
                "이윤혁",
                "이장훈",
                "윤학병"
            ]
        },
        {
            "id": "벤허",
            "group": 1,
            "href": "/movie/bi/mi/basic.nhn?code=10058",
            "genre": [
                "드라마",
                "액션",
                "모험",
                "멜로/로맨스"
            ],
            "director": [
                "윌리엄 와일러"
            ],
            "actor": [
                "찰톤 헤스톤",
                "잭 호킨스",
                "하야 하라릿"
            ]
        }
    ],
    "genre_data": [
        {
            "title": "드라마",
            "group": 1
        },
        {
            "title": "가족",
            "group": 2
        },
        {
            "title": "SF",
            "group": 3
        },
        {
            "title": "다큐멘터리",
            "group": 4
        },
        {
            "title": "코미디",
            "group": 5
        },
        {
            "title": "멜로/로맨스",
            "group": 6
        }
    ],
    "data": [
        {
            "movie_n": 251,
            "genre_n": 6
        }
    ]
}